Metadata-Version: 1.0
Name: LDScriptures
Version: 0.3.3
Summary: Powerful tool for getting the LDS (mormon) scriptures in your python script.
Home-page: https://github.com/tgsec/ldscriptures
Author: CustodiSec
Author-email: tgb1@protonmail.com
License: UNKNOWN
Keywords: mormon,lds,latter,day,saints,book of mormon,scriptures,bible,pearl of great price,doctrine and convenants,church of jesus christ,parse,citation
Platform: UNKNOWN
